scientific_writer/__init__.py
scientific_writer/api.py
scientific_writer/cli.py
scientific_writer/core.py
scientific_writer/models.py
scientific_writer/utils.py
scientific_writer/.claude/WRITER.md
scientific_writer/.claude/skills/citation-management/SKILL.md
scientific_writer/.claude/skills/citation-management/assets/bibtex_template.bib
scientific_writer/.claude/skills/citation-management/assets/citation_checklist.md
scientific_writer/.claude/skills/citation-management/references/bibtex_formatting.md
scientific_writer/.claude/skills/citation-management/references/citation_validation.md
scientific_writer/.claude/skills/citation-management/references/google_scholar_search.md
scientific_writer/.claude/skills/citation-management/references/metadata_extraction.md
scientific_writer/.claude/skills/citation-management/references/pubmed_search.md
scientific_writer/.claude/skills/citation-management/scripts/doi_to_bibtex.py
scientific_writer/.claude/skills/citation-management/scripts/extract_metadata.py
scientific_writer/.claude/skills/citation-management/scripts/format_bibtex.py
scientific_writer/.claude/skills/citation-management/scripts/search_google_scholar.py
scientific_writer/.claude/skills/citation-management/scripts/search_pubmed.py
scientific_writer/.claude/skills/citation-management/scripts/validate_citations.py
scientific_writer/.claude/skills/clinical-decision-support/README.md
scientific_writer/.claude/skills/clinical-decision-support/SKILL.md
scientific_writer/.claude/skills/clinical-decision-support/assets/biomarker_report_template.tex
scientific_writer/.claude/skills/clinical-decision-support/assets/clinical_pathway_template.tex
scientific_writer/.claude/skills/clinical-decision-support/assets/cohort_analysis_template.tex
scientific_writer/.claude/skills/clinical-decision-support/assets/color_schemes.tex
scientific_writer/.claude/skills/clinical-decision-support/assets/example_gbm_cohort.md
scientific_writer-2.10.3.dist-info/METADATA
scientific_writer-2.10.3.dist-info/WHEEL
scientific_writer-2.10.3.dist-info/entry_points.txt
scientific_writer-2.10.3.dist-info/licenses/LICENSE
scientific_writer-2.10.3.dist-info/RECORD
