Metadata-Version: 2.4
Name: scientific-writer
Version: 2.10.3
Summary: Deep research and writing tool - combines AI-driven deep research with well-formatted written outputs. Generates publication-ready scientific documents with verified citations.
License: MIT
License-File: LICENSE
Requires-Python: >=3.10
Requires-Dist: claude-agent-sdk>=0.1.0
Requires-Dist: pymupdf>=1.24.0
Requires-Dist: python-dotenv>=1.0.0
Requires-Dist: requests>=2.31.0
